README.md
setup.cfg
setup.py
predictionary/__init__.py
predictionary/data.py
predictionary/source.py
predictionary/visualize.py
predictionary.egg-info/PKG-INFO
predictionary.egg-info/SOURCES.txt
predictionary.egg-info/dependency_links.txt
predictionary.egg-info/requires.txt
predictionary.egg-info/top_level.txt